gaql_builder/__init__.py
gaql_builder/main.py
gaql_builder-1.0.2.dist-info/LICENSE
gaql_builder-1.0.2.dist-info/METADATA
gaql_builder-1.0.2.dist-info/WHEEL
gaql_builder-1.0.2.dist-info/entry_points.txt
gaql_builder-1.0.2.dist-info/top_level.txt
gaql_builder-1.0.2.dist-info/RECORD
