Metadata-Version: 2.1
Name: gaql-builder
Version: 1.0.2
Summary: Generating GAQL tool
Home-page: https://github.com/yo8568/gaql-builder
Author: Shao-Tung Change
Author-email: yo8568@gmail.com
License: UNKNOWN
Platform: UNKNOWN
Classifier: Programming Language :: Python
Classifier: Programming Language :: Python :: 2
Classifier: Programming Language :: Python :: 2.7
Classifier: Programming Language :: Python :: 3
Classifier: Programming Language :: Python :: 3.4
Classifier: Programming Language :: Python :: 3.5
Classifier: Programming Language :: Python :: 3.6
Classifier: License :: OSI Approved :: MIT License
Classifier: Operating System :: OS Independent
